{
  "timestamp": "20260307_080905",
  "run_id": "506f2ea7",
  "file_name": "acg_upperGI_bleed.pdf",
  "document_type": "acute_protocol",
  "engine_used": "AcuteProtocolEngine",
  "confidence": 0.95,
  "body_systems": [
    "gastrointestinal"
  ],
  "modules_activated": [
    "urgency_triage",
    "stabilization_steps",
    "critical_thresholds",
    "emergency_medications",
    "escalation_triggers",
    "disposition"
  ],
  "raw_text_chars": 112379,
  "validation_passed": false,
  "validation_warnings": [
    "Missing top-level key: 'governance'",
    "source.source_id is missing \u2014 link to ite_refs manifest not established"
  ],
  "recommendations_count": 35,
  "thresholds_count": 19,
  "medications_count": 13
}