{
  "timestamp": "20260305_115205",
  "run_id": "ddfd7b8a",
  "file_name": "aafp_lumbar_backpain.pdf",
  "document_type": "chronic_guideline",
  "engine_used": "ChronicRiskEngine",
  "confidence": 0.85,
  "body_systems": [
    "musculoskeletal",
    "neurologic"
  ],
  "modules_activated": [
    "disease_definition",
    "diagnostic_thresholds",
    "risk_stratification",
    "escalation_ladder",
    "medication_management",
    "monitoring_schedule"
  ],
  "raw_text_chars": 13431,
  "validation_passed": false,
  "validation_warnings": [
    "Missing top-level key: 'governance'",
    "source.source_id is missing \u2014 link to ite_refs manifest not established"
  ],
  "recommendations_count": 6,
  "thresholds_count": 4,
  "medications_count": 4
}